discord_plays_nationstates/__init__.py
discord_plays_nationstates/__main__.py
discord_plays_nationstates/core.py
discord_plays_nationstates/run.py
discord_plays_nationstates/utils.py
discord_plays_nationstates-0.1.1.dist-info/DESCRIPTION.rst
discord_plays_nationstates-0.1.1.dist-info/METADATA
discord_plays_nationstates-0.1.1.dist-info/RECORD
discord_plays_nationstates-0.1.1.dist-info/WHEEL
discord_plays_nationstates-0.1.1.dist-info/entry_points.txt
discord_plays_nationstates-0.1.1.dist-info/metadata.json
discord_plays_nationstates-0.1.1.dist-info/top_level.txt
