Metadata-Version: 2.0
Name: discord-plays-nationstates
Version: 0.1.1
Summary: A discord bot that answers issues as a NationStates nation
Home-page: https://github.com/micha030201/discord-plays-nationstates
Author: Михаил Лебедев
Author-email: micha030201@gmail.com
License: AGPLv3+
Keywords: nationstates chatbot
Platform: UNKNOWN
Classifier: Development Status :: 3 - Alpha
Classifier: Intended Audience :: Developers
Classifier: Intended Audience :: End Users/Desktop
Classifier: Topic :: Internet
Classifier: Topic :: Games/Entertainment :: Simulation
Classifier: Natural Language :: English
Classifier: License :: OSI Approved :: GNU Affero General Public License v3 or later (AGPLv3+)
Classifier: Programming Language :: Python :: 3.6
Classifier: Framework :: AsyncIO
Requires-Python: >=3.6.1
Requires-Dist: aionationstates
Requires-Dist: discord.py
